setup.py
di_export_cli/__init__.py
di_export_cli/apiexecutor.py
di_export_cli/cli.py
di_export_cli/exports.py
di_export_cli/httprequests.py
di_export_cli/parser.py
di_export_cli/settings_handler.py
di_export_cli/utils.py
di_export_cli/swagger/__init__.py
di_export_cli/swagger/swagger_client/__init__.py
di_export_cli/swagger/swagger_client/api_client.py
di_export_cli/swagger/swagger_client/configuration.py
di_export_cli/swagger/swagger_client/rest.py
di_export_cli/swagger/swagger_client/apis/__init__.py
di_export_cli/swagger/swagger_client/apis/accountresource_api.py
di_export_cli/swagger/swagger_client/apis/basicerrorcontroller_api.py
di_export_cli/swagger/swagger_client/apis/endpointmvcadapter_api.py
di_export_cli/swagger/swagger_client/apis/environmentmvcendpoint_api.py
di_export_cli/swagger/swagger_client/apis/exportresource_api.py
di_export_cli/swagger/swagger_client/apis/exportworkqueueresource_api.py
di_export_cli/swagger/swagger_client/apis/haljsonmvcendpoint_api.py
di_export_cli/swagger/swagger_client/apis/healthmvcendpoint_api.py
di_export_cli/swagger/swagger_client/apis/metricsmvcendpoint_api.py
di_export_cli/swagger/swagger_client/apis/templateresource_api.py
di_export_cli/swagger/swagger_client/models/__init__.py
di_export_cli/swagger/swagger_client/models/export.py
di_export_cli/swagger/swagger_client/models/export_account.py
di_export_cli/swagger/swagger_client/models/export_account_list.py
di_export_cli/swagger/swagger_client/models/export_config.py
di_export_cli/swagger/swagger_client/models/export_config_meta_data.py
di_export_cli/swagger/swagger_client/models/export_files_response.py
di_export_cli/swagger/swagger_client/models/export_instance.py
di_export_cli/swagger/swagger_client/models/export_instances_response.py
di_export_cli/swagger/swagger_client/models/export_result.py
di_export_cli/swagger/swagger_client/models/export_result_file.py
di_export_cli/swagger/swagger_client/models/export_template.py
ensighten_exports.egg-info/PKG-INFO
ensighten_exports.egg-info/SOURCES.txt
ensighten_exports.egg-info/dependency_links.txt
ensighten_exports.egg-info/entry_points.txt
ensighten_exports.egg-info/requires.txt
ensighten_exports.egg-info/top_level.txt