Metadata-Version: 1.1
Name: ensighten-exports
Version: 0.65
Summary: Ensighten exports command line interface
Home-page: https://bitbucket.org/ensighten-ondemand/dataintelligence-exports-cli
Author: UNKNOWN
Author-email: UNKNOWN
License: UNKNOWN
Platform: UNKNOWN
Classifier: Development Status :: 4 - Beta
Classifier: Programming Language :: Python :: 2.7
